sloth_ci/validators/gitlab.py
sloth_ci.validators.gitlab-1.0.2.dist-info/DESCRIPTION.rst
sloth_ci.validators.gitlab-1.0.2.dist-info/METADATA
sloth_ci.validators.gitlab-1.0.2.dist-info/RECORD
sloth_ci.validators.gitlab-1.0.2.dist-info/WHEEL
sloth_ci.validators.gitlab-1.0.2.dist-info/metadata.json
sloth_ci.validators.gitlab-1.0.2.dist-info/top_level.txt
